odoo/addons/stock_picking_auto_create_lot/README.rst
odoo/addons/stock_picking_auto_create_lot/__init__.py
odoo/addons/stock_picking_auto_create_lot/__manifest__.py
odoo/addons/stock_picking_auto_create_lot/i18n/es.po
odoo/addons/stock_picking_auto_create_lot/i18n/stock_picking_auto_create_lot.pot
odoo/addons/stock_picking_auto_create_lot/i18n/zh_CN.po
odoo/addons/stock_picking_auto_create_lot/models/__init__.py
odoo/addons/stock_picking_auto_create_lot/models/product.py
odoo/addons/stock_picking_auto_create_lot/models/stock_move.py
odoo/addons/stock_picking_auto_create_lot/models/stock_move_line.py
odoo/addons/stock_picking_auto_create_lot/models/stock_picking.py
odoo/addons/stock_picking_auto_create_lot/models/stock_picking_type.py
odoo/addons/stock_picking_auto_create_lot/readme/CONFIGURE.rst
odoo/addons/stock_picking_auto_create_lot/readme/CONTRIBUTORS.rst
odoo/addons/stock_picking_auto_create_lot/readme/DESCRIPTION.rst
odoo/addons/stock_picking_auto_create_lot/readme/USAGE.rst
odoo/addons/stock_picking_auto_create_lot/static/description/icon.png
odoo/addons/stock_picking_auto_create_lot/static/description/index.html
odoo/addons/stock_picking_auto_create_lot/tests/__init__.py
odoo/addons/stock_picking_auto_create_lot/tests/common.py
odoo/addons/stock_picking_auto_create_lot/tests/test_stock_picking_auto_create_lot.py
odoo/addons/stock_picking_auto_create_lot/views/product_views.xml
odoo/addons/stock_picking_auto_create_lot/views/stock_picking_type_views.xml
odoo13_addon_stock_picking_auto_create_lot-13.0.1.1.0.dist-info/METADATA
odoo13_addon_stock_picking_auto_create_lot-13.0.1.1.0.dist-info/WHEEL
odoo13_addon_stock_picking_auto_create_lot-13.0.1.1.0.dist-info/top_level.txt
odoo13_addon_stock_picking_auto_create_lot-13.0.1.1.0.dist-info/RECORD
